finitelycomputable/tests/tests_with_import_guards/__init__.py
finitelycomputable/tests/tests_with_import_guards/test_cherrypy_mount.py
finitelycomputable/tests/tests_with_import_guards/test_cherrypy_mount_helloworld.py
finitelycomputable/tests/tests_with_import_guards/test_django_apps.py
finitelycomputable/tests/tests_with_import_guards/test_falcon_addroute.py
finitelycomputable/tests/tests_with_import_guards/test_falcon_addroute_helloworld.py
finitelycomputable/tests/tests_with_import_guards/test_falcon_addroute_idtrust.py
finitelycomputable/tests/tests_with_import_guards/test_flask_blueprints.py
finitelycomputable/tests/tests_with_import_guards/test_flask_blueprints_helloworld.py
finitelycomputable/tests/tests_with_import_guards/test_flask_blueprints_idtrust.py
finitelycomputable/tests/tests_with_import_guards/test_flask_dispatcher.py
finitelycomputable/tests/tests_with_import_guards/test_flask_dispatcher_helloworld.py
finitelycomputable/tests/tests_with_import_guards/test_flask_dispatcher_idtrust.py
finitelycomputable/tests/tests_with_import_guards/test_helloworld_cherrypy.py
finitelycomputable/tests/tests_with_import_guards/test_helloworld_django.py
finitelycomputable/tests/tests_with_import_guards/test_helloworld_falcon.py
finitelycomputable/tests/tests_with_import_guards/test_helloworld_flask.py
finitelycomputable/tests/tests_with_import_guards/test_helloworld_morepath.py
finitelycomputable/tests/tests_with_import_guards/test_helloworld_quart.py
finitelycomputable/tests/tests_with_import_guards/test_idtrust_django.py
finitelycomputable/tests/tests_with_import_guards/test_idtrust_falcon.py
finitelycomputable/tests/tests_with_import_guards/test_idtrust_flask.py
finitelycomputable/tests/tests_with_import_guards/test_morepath_mount.py
finitelycomputable/tests/tests_with_import_guards/test_morepath_mount_helloworld.py
finitelycomputable_tests-25.7.dist-info/METADATA
finitelycomputable_tests-25.7.dist-info/WHEEL
finitelycomputable_tests-25.7.dist-info/entry_points.txt
finitelycomputable_tests-25.7.dist-info/top_level.txt
finitelycomputable_tests-25.7.dist-info/RECORD
